[
    {
      "institution": "Chattogram Veterinary and Animal Sciences University",
      "degree": "Bachelor of Science (B.Sc.) in Fisheries",
      "year": "2020 - 2024",
      "result": "3.71/4.00"
    },
    {
      "institution": "Dhaka City College",
      "degree": "Higher Secondary",
      "year": "2019",
      "result": "5.00/5.00"
    },
    {
      "institution": "Monipur High School & College",
      "degree": "Secondary",
      "year": "2017",
      "result": "5.00/5.00"
    }
  ]
  